easy_fsm/__init__.py
easy_fsm/context.py
easy_fsm/state.py
easy_fsm/state_machine.py
LICENSE.txt
easy_fsm-0.2.0.dist-info/LICENSE.txt
easy_fsm-0.2.0.dist-info/WHEEL
easy_fsm-0.2.0.dist-info/METADATA
easy_fsm-0.2.0.dist-info/RECORD
