Metadata-Version: 2.1
Name: easy-fsm
Version: 0.2.0
Summary: Easy to implement Finite State Machines
Home-page: https://github.com/linkdd/easy_fsm
License: MIT
Keywords: easy,finite,state,machine,fsm
Author: David Delassus
Author-email: david.jose.delassus@gmail.com
Requires-Python: >=3.10,<4.0
Classifier: Development Status :: 3 - Alpha
Classifier: Intended Audience :: Developers
Classifier: License :: OSI Approved :: MIT License
Classifier: Operating System :: OS Independent
Classifier: Programming Language :: Python
Classifier: Programming Language :: Python :: 3
Classifier: Programming Language :: Python :: 3.10
Classifier: Topic :: Software Development :: Libraries
Classifier: Topic :: Utilities
Classifier: Typing :: Typed
Project-URL: Repository, https://github.com/linkdd/easy_fsm
